README.md
setup.py
dsmemail/__init__.py
dsmemail/check.py
dsmemail/sendmail.py
dsmemail.egg-info/PKG-INFO
dsmemail.egg-info/SOURCES.txt
dsmemail.egg-info/dependency_links.txt
dsmemail.egg-info/requires.txt
dsmemail.egg-info/top_level.txt
dsmemail/utils/__init__.py
dsmemail/utils/airflow_email.py
test/test.py